vimtk/__init__.py
vimtk/_dirty.py
vimtk/core.py
vimtk/cplat.py
vimtk/jedi_monkeypatch.py
vimtk/pyinspect.py
vimtk/win32_ctrl.py
vimtk/xctrl.py
vimtk/_demo/__init__.py
vimtk/_demo/vimmock/__init__.py
vimtk/_demo/vimmock/mocked.py
vimtk/_demo/vimmock/tests.py
vimtk-0.3.1.dist-info/LICENSE
vimtk-0.3.1.dist-info/METADATA
vimtk-0.3.1.dist-info/WHEEL
vimtk-0.3.1.dist-info/top_level.txt
vimtk-0.3.1.dist-info/RECORD
